plantuml_markdown/__init__.py
plantuml_markdown/plantuml_markdown.py
plantuml_markdown-3.11.0.dist-info/LICENSE
plantuml_markdown-3.11.0.dist-info/METADATA
plantuml_markdown-3.11.0.dist-info/WHEEL
plantuml_markdown-3.11.0.dist-info/entry_points.txt
plantuml_markdown-3.11.0.dist-info/top_level.txt
plantuml_markdown-3.11.0.dist-info/RECORD
