Metadata-Version: 2.1
Name: plantuml-markdown
Version: 3.11.0
Summary: A PlantUML plugin for Markdown
Home-page: https://github.com/mikitex70/plantuml-markdown
Author: Michele Tessaro
Author-email: michele.tessaro.tex@gmail.com
Keywords: Markdown,typesetting,include,plugin,extension
Classifier: Programming Language :: Python
Classifier: License :: OSI Approved :: BSD License
Classifier: Operating System :: OS Independent
Classifier: Development Status :: 5 - Production/Stable
Classifier: Topic :: Software Development :: Documentation
Classifier: Topic :: Software Development :: Libraries :: Python Modules
Classifier: Topic :: Text Processing :: Filters
Classifier: Topic :: Text Processing :: Markup :: HTML
License-File: LICENSE
Requires-Dist: Markdown
Requires-Dist: requests
Requires-Dist: six
